odoo/addons/mgmtsystem_objective/README.rst
odoo/addons/mgmtsystem_objective/__init__.py
odoo/addons/mgmtsystem_objective/__manifest__.py
odoo/addons/mgmtsystem_objective/demo/mgmtsystem_objective.xml
odoo/addons/mgmtsystem_objective/i18n/it.po
odoo/addons/mgmtsystem_objective/i18n/mgmtsystem_objective.pot
odoo/addons/mgmtsystem_objective/models/__init__.py
odoo/addons/mgmtsystem_objective/models/mgmtsystem_indicator.py
odoo/addons/mgmtsystem_objective/models/mgmtsystem_indicator_value.py
odoo/addons/mgmtsystem_objective/models/mgmtsystem_objective.py
odoo/addons/mgmtsystem_objective/readme/CONTRIBUTORS.md
odoo/addons/mgmtsystem_objective/readme/DESCRIPTION.md
odoo/addons/mgmtsystem_objective/readme/ROADMAP.md
odoo/addons/mgmtsystem_objective/security/ir.model.access.csv
odoo/addons/mgmtsystem_objective/security/security.xml
odoo/addons/mgmtsystem_objective/static/description/icon.png
odoo/addons/mgmtsystem_objective/static/description/index.html
odoo/addons/mgmtsystem_objective/static/src/components/objective_state_selection/objective_state_selection.esm.js
odoo/addons/mgmtsystem_objective/static/tests/components/objective_state_selection.test.js
odoo/addons/mgmtsystem_objective/tests/__init__.py
odoo/addons/mgmtsystem_objective/tests/test_js.py
odoo/addons/mgmtsystem_objective/tests/test_objective.py
odoo/addons/mgmtsystem_objective/views/mgmtsystem_indicator.xml
odoo/addons/mgmtsystem_objective/views/mgmtsystem_indicator_value.xml
odoo/addons/mgmtsystem_objective/views/mgmtsystem_objective.xml
odoo_addon_mgmtsystem_objective-18.0.1.0.0.4.dist-info/METADATA
odoo_addon_mgmtsystem_objective-18.0.1.0.0.4.dist-info/WHEEL
odoo_addon_mgmtsystem_objective-18.0.1.0.0.4.dist-info/top_level.txt
odoo_addon_mgmtsystem_objective-18.0.1.0.0.4.dist-info/RECORD
